docs/conf.py
simplesip/__init__.py
simplesip/client.py
simplesip/examples/__init__.py
simplesip/examples/demo.py
simplesip-0.1.5.dist-info/licenses/LICENSE
simplesip-0.1.5.dist-info/METADATA
simplesip-0.1.5.dist-info/WHEEL
simplesip-0.1.5.dist-info/entry_points.txt
simplesip-0.1.5.dist-info/top_level.txt
simplesip-0.1.5.dist-info/RECORD
