Metadata-Version: 2.4
Name: simplesip
Version: 0.1.5
Summary: Simple SIP client library with RTP audio streaming capabilities
Home-page: https://github.com/Awaiskhan404/simplesip
Author: Awais Khan
Author-email: Awais khan <contact@awaiskhan.com.pk>
License: MIT
Project-URL: Homepage, https://github.com/Awaiskhan404/simplesip
Project-URL: Documentation, https://simplesip.readthedocs.io/
Project-URL: Repository, https://github.com/Awaiskhan404/simplesip.git
Project-URL: Bug Tracker, https://github.com/Awaiskhan404/simplesip/issues
Keywords: sip,voip,rtp,audio,streaming,telephony,simple
Classifier: Development Status :: 3 - Alpha
Classifier: Intended Audience :: Developers
Classifier: License :: OSI Approved :: MIT License
Classifier: Operating System :: OS Independent
Classifier: Programming Language :: Python :: 3
Classifier: Programming Language :: Python :: 3.8
Classifier: Programming Language :: Python :: 3.9
Classifier: Programming Language :: Python :: 3.10
Classifier: Programming Language :: Python :: 3.11
Classifier: Programming Language :: Python :: 3.12
Classifier: Programming Language :: Python :: 3.13
Classifier: Topic :: Communications :: Telephony
Classifier: Topic :: Internet :: WWW/HTTP
Classifier: Topic :: Software Development :: Libraries :: Python Modules
Requires-Python: >=3.8
License-File: LICENSE
Requires-Dist: g722>=1.2.1
Requires-Dist: numpy>=1.19.0
Provides-Extra: audio
Requires-Dist: pyaudio>=0.2.11; extra == "audio"
Provides-Extra: dev
Requires-Dist: pytest>=6.0; extra == "dev"
Requires-Dist: pytest-cov>=2.0; extra == "dev"
Requires-Dist: black>=21.0; extra == "dev"
Requires-Dist: flake8>=3.8; extra == "dev"
Requires-Dist: mypy>=0.800; extra == "dev"
Requires-Dist: isort>=5.0; extra == "dev"
Dynamic: author
Dynamic: home-page
Dynamic: license-file
Dynamic: requires-python
